odoo/addons/project_forecast_line_milestone/README.rst
odoo/addons/project_forecast_line_milestone/__init__.py
odoo/addons/project_forecast_line_milestone/__manifest__.py
odoo/addons/project_forecast_line_milestone/i18n/it.po
odoo/addons/project_forecast_line_milestone/i18n/project_forecast_line_milestone.pot
odoo/addons/project_forecast_line_milestone/models/__init__.py
odoo/addons/project_forecast_line_milestone/models/project_task.py
odoo/addons/project_forecast_line_milestone/readme/CONTRIBUTORS.rst
odoo/addons/project_forecast_line_milestone/readme/DESCRIPTION.rst
odoo/addons/project_forecast_line_milestone/static/description/icon.png
odoo/addons/project_forecast_line_milestone/static/description/index.html
odoo/addons/project_forecast_line_milestone/tests/__init__.py
odoo/addons/project_forecast_line_milestone/tests/test_forecast_line_milestone.py
odoo14_addon_project_forecast_line_milestone-14.0.1.0.1.dev4.dist-info/METADATA
odoo14_addon_project_forecast_line_milestone-14.0.1.0.1.dev4.dist-info/WHEEL
odoo14_addon_project_forecast_line_milestone-14.0.1.0.1.dev4.dist-info/top_level.txt
odoo14_addon_project_forecast_line_milestone-14.0.1.0.1.dev4.dist-info/RECORD
