Metadata-Version: 2.1
Name: odoo14-addon-project_forecast_line_milestone
Version: 14.0.1.0.1.dev4
Summary: Project Forecast Line dates according to Milestone target date
Home-page: https://github.com/OCA/project
Author: Therp BV, Odoo Community Association (OCA)
Author-email: support@odoo-community.org
License: AGPL-3
Classifier: Programming Language :: Python
Classifier: Framework :: Odoo
Classifier: Framework :: Odoo :: 14.0
Classifier: License :: OSI Approved :: GNU Affero General Public License v3
Classifier: Development Status :: 3 - Alpha
Requires-Python: >=3.6
Requires-Dist: odoo14-addon-project-forecast-line-priority
Requires-Dist: odoo14-addon-project-milestone
Requires-Dist: odoo<14.1dev,>=14.0a
